ctracing.py
ctracing-1.1.0.dist-info/METADATA
ctracing-1.1.0.dist-info/WHEEL
ctracing-1.1.0.dist-info/top_level.txt
ctracing-1.1.0.dist-info/RECORD
